musfeat/__init__.py
musfeat/musfeat.py
musfeat/analysis/__init__.py
musfeat/analysis/audio_analysis.py
musfeat/helper/__init__.py
musfeat/helper/settings.py
musfeat/models/__init__.py
musfeat/models/audio_models.py
MusFeat-1.0.3.dist-info/LICENSE.txt
MusFeat-1.0.3.dist-info/METADATA
MusFeat-1.0.3.dist-info/WHEEL
MusFeat-1.0.3.dist-info/top_level.txt
MusFeat-1.0.3.dist-info/RECORD
