Metadata-Version: 2.1
Name: MusFeat
Version: 1.0.3
Summary: UNKNOWN
Home-page: UNKNOWN
Author: David Martin-Gutierrez
Author-email: dmargutierrez@gmail.com
License: MIT
Platform: UNKNOWN
Requires-Python: >=3.6
Requires-Dist: pandas
Requires-Dist: numpy
Requires-Dist: coloredlogs
Requires-Dist: pymongo
Requires-Dist: librosa
Requires-Dist: pydub
Requires-Dist: scikit-learn
Requires-Dist: matplotlib
